[["0","1",{"allocated":0.0,"capacity":1000.0,"flows":[],"id":"10000"}],["1","0",{"allocated":0.0,"capacity":1000.0,"flows":[],"id":"10010"}],["1","2",{"allocated":0.0,"capacity":1000.0,"flows":[],"id":"10001"}],["2","1",{"allocated":0.0,"capacity":1000.0,"flows":[],"id":"10011"}],["1","3",{"allocated":0.0,"capacity":1000.0,"flows":[],"id":"10002"}],["3","1",{"allocated":0.0,"capacity":1000.0,"flows":[],"id":"10012"}],["2","4",{"allocated":0.0,"capacity":1000.0,"flows":[],"id":"10003"}],["4","2",{"allocated":0.0,"capacity":1000.0,"flows":[],"id":"10013"}],["2","5",{"allocated":0.0,"capacity":1000.0,"flows":[],"id":"10004"}],["5","2",{"allocated":0.0,"capacity":1000.0,"flows":[],"id":"10014"}],["3","6",{"allocated":0.0,"capacity":1000.0,"flows":[],"id":"10005"}],["6","3",{"allocated":0.0,"capacity":1000.0,"flows":[],"id":"10015"}],["3","7",{"allocated":0.0,"capacity":1000.0,"flows":[],"id":"10006"}],["7","3",{"allocated":0.0,"capacity":1000.0,"flows":[],"id":"10016"}],["4","8",{"allocated":0.0,"capacity":1000.0,"flows":[],"id":"10007"}],["8","4",{"allocated":0.0,"capacity":1000.0,"flows":[],"id":"10017"}],["4","9",{"allocated":0.0,"capacity":1000.0,"flows":[],"id":"10008"}],["9","4",{"allocated":0.0,"capacity":1000.0,"flows":[],"id":"10018"}],["5","10",{"allocated":0.0,"capacity":1000.0,"flows":[],"id":"10009"}],["10","5",{"allocated":0.0,"capacity":1000.0,"flows":[],"id":"10019"}],["5","11",{"allocated":0.0,"capacity":1000.0,"flows":[],"id":"100010"}],["11","5",{"allocated":0.0,"capacity":1000.0,"flows":[],"id":"100110"}],["6","12",{"allocated":0.0,"capacity":1000.0,"flows":[],"id":"100011"}],["12","6",{"allocated":0.0,"capacity":1000.0,"flows":[],"id":"100111"}],["6","13",{"allocated":0.0,"capacity":1000.0,"flows":[],"id":"100012"}],["13","6",{"allocated":0.0,"capacity":1000.0,"flows":[],"id":"100112"}],["7","14",{"allocated":0.0,"capacity":1000.0,"flows":[],"id":"100013"}],["14","7",{"allocated":0.0,"capacity":1000.0,"flows":[],"id":"100113"}],["7","15",{"allocated":0.0,"capacity":1000.0,"flows":[],"id":"100014"}],["15","7",{"allocated":0.0,"capacity":1000.0,"flows":[],"id":"100114"}],["8","16",{"allocated":0.0,"capacity":1000.0,"flows":[],"id":"100015"}],["16","8",{"allocated":0.0,"capacity":1000.0,"flows":[],"id":"100115"}],["8","17",{"allocated":0.0,"capacity":1000.0,"flows":[],"id":"100016"}],["17","8",{"allocated":0.0,"capacity":1000.0,"flows":[],"id":"100116"}],["9","18",{"allocated":0.0,"capacity":1000.0,"flows":[],"id":"100017"}],["18","9",{"allocated":0.0,"capacity":1000.0,"flows":[],"id":"100117"}],["9","19",{"allocated":0.0,"capacity":1000.0,"flows":[],"id":"100018"}],["19","9",{"allocated":0.0,"capacity":1000.0,"flows":[],"id":"100118"}],["10","20",{"allocated":0.0,"capacity":1000.0,"flows":[],"id":"100019"}],["20","10",{"allocated":0.0,"capacity":1000.0,"flows":[],"id":"100119"}],["10","21",{"allocated":0.0,"capacity":1000.0,"flows":[],"id":"100020"}],["21","10",{"allocated":0.0,"capacity":1000.0,"flows":[],"id":"100120"}],["11","22",{"allocated":0.0,"capacity":1000.0,"flows":[],"id":"100021"}],["22","11",{"allocated":0.0,"capacity":1000.0,"flows":[],"id":"100121"}],["11","23",{"allocated":0.0,"capacity":1000.0,"flows":[],"id":"100022"}],["23","11",{"allocated":0.0,"capacity":1000.0,"flows":[],"id":"100122"}],["12","24",{"allocated":0.0,"capacity":1000.0,"flows":[],"id":"100023"}],["24","12",{"allocated":0.0,"capacity":1000.0,"flows":[],"id":"100123"}],["12","25",{"allocated":0.0,"capacity":1000.0,"flows":[],"id":"100024"}],["25","12",{"allocated":0.0,"capacity":1000.0,"flows":[],"id":"100124"}],["13","26",{"allocated":0.0,"capacity":1000.0,"flows":[],"id":"100025"}],["26","13",{"allocated":0.0,"capacity":1000.0,"flows":[],"id":"100125"}],["13","27",{"allocated":0.0,"capacity":1000.0,"flows":[],"id":"100026"}],["27","13",{"allocated":0.0,"capacity":1000.0,"flows":[],"id":"100126"}],["14","28",{"allocated":0.0,"capacity":1000.0,"flows":[],"id":"100027"}],["28","14",{"allocated":0.0,"capacity":1000.0,"flows":[],"id":"100127"}],["14","29",{"allocated":0.0,"capacity":1000.0,"flows":[],"id":"100028"}],["29","14",{"allocated":0.0,"capacity":1000.0,"flows":[],"id":"100128"}],["15","30",{"allocated":0.0,"capacity":1000.0,"flows":[],"id":"100029"}],["30","15",{"allocated":0.0,"capacity":1000.0,"flows":[],"id":"100129"}],["15","31",{"allocated":0.0,"capacity":1000.0,"flows":[],"id":"100030"}],["31","15",{"allocated":0.0,"capacity":1000.0,"flows":[],"id":"100130"}],["16","32",{"allocated":0.0,"capacity":1000.0,"flows":[],"id":"100031"}],["32","16",{"allocated":0.0,"capacity":1000.0,"flows":[],"id":"100131"}],["16","33",{"allocated":0.0,"capacity":1000.0,"flows":[],"id":"100032"}],["33","16",{"allocated":0.0,"capacity":1000.0,"flows":[],"id":"100132"}],["17","34",{"allocated":0.0,"capacity":1000.0,"flows":[],"id":"100033"}],["34","17",{"allocated":0.0,"capacity":1000.0,"flows":[],"id":"100133"}],["17","35",{"allocated":0.0,"capacity":1000.0,"flows":[],"id":"100034"}],["35","17",{"allocated":0.0,"capacity":1000.0,"flows":[],"id":"100134"}],["18","36",{"allocated":0.0,"capacity":1000.0,"flows":[],"id":"100035"}],["36","18",{"allocated":0.0,"capacity":1000.0,"flows":[],"id":"100135"}],["18","37",{"allocated":0.0,"capacity":1000.0,"flows":[],"id":"100036"}],["37","18",{"allocated":0.0,"capacity":1000.0,"flows":[],"id":"100136"}],["19","38",{"allocated":0.0,"capacity":1000.0,"flows":[],"id":"100037"}],["38","19",{"allocated":0.0,"capacity":1000.0,"flows":[],"id":"100137"}],["19","39",{"allocated":0.0,"capacity":1000.0,"flows":[],"id":"100038"}],["39","19",{"allocated":0.0,"capacity":1000.0,"flows":[],"id":"100138"}],["20","40",{"allocated":0.0,"capacity":1000.0,"flows":[],"id":"100039"}],["40","20",{"allocated":0.0,"capacity":1000.0,"flows":[],"id":"100139"}],["20","41",{"allocated":0.0,"capacity":1000.0,"flows":[],"id":"100040"}],["41","20",{"allocated":0.0,"capacity":1000.0,"flows":[],"id":"100140"}],["21","42",{"allocated":0.0,"capacity":1000.0,"flows":[],"id":"100041"}],["42","21",{"allocated":0.0,"capacity":1000.0,"flows":[],"id":"100141"}],["21","43",{"allocated":0.0,"capacity":1000.0,"flows":[],"id":"100042"}],["43","21",{"allocated":0.0,"capacity":1000.0,"flows":[],"id":"100142"}],["22","44",{"allocated":0.0,"capacity":1000.0,"flows":[],"id":"100043"}],["44","22",{"allocated":0.0,"capacity":1000.0,"flows":[],"id":"100143"}],["22","45",{"allocated":0.0,"capacity":1000.0,"flows":[],"id":"100044"}],["45","22",{"allocated":0.0,"capacity":1000.0,"flows":[],"id":"100144"}],["23","46",{"allocated":0.0,"capacity":1000.0,"flows":[],"id":"100045"}],["46","23",{"allocated":0.0,"capacity":1000.0,"flows":[],"id":"100145"}],["23","47",{"allocated":0.0,"capacity":1000.0,"flows":[],"id":"100046"}],["47","23",{"allocated":0.0,"capacity":1000.0,"flows":[],"id":"100146"}],["24","48",{"allocated":0.0,"capacity":1000.0,"flows":[],"id":"100047"}],["48","24",{"allocated":0.0,"capacity":1000.0,"flows":[],"id":"100147"}],["24","49",{"allocated":0.0,"capacity":1000.0,"flows":[],"id":"100048"}],["49","24",{"allocated":0.0,"capacity":1000.0,"flows":[],"id":"100148"}],["25","50",{"allocated":0.0,"capacity":1000.0,"flows":[],"id":"100049"}],["50","25",{"allocated":0.0,"capacity":1000.0,"flows":[],"id":"100149"}],["25","51",{"allocated":0.0,"capacity":1000.0,"flows":[],"id":"100050"}],["51","25",{"allocated":0.0,"capacity":1000.0,"flows":[],"id":"100150"}],["26","52",{"allocated":0.0,"capacity":1000.0,"flows":[],"id":"100051"}],["52","26",{"allocated":0.0,"capacity":1000.0,"flows":[],"id":"100151"}],["26","53",{"allocated":0.0,"capacity":1000.0,"flows":[],"id":"100052"}],["53","26",{"allocated":0.0,"capacity":1000.0,"flows":[],"id":"100152"}],["27","54",{"allocated":0.0,"capacity":1000.0,"flows":[],"id":"100053"}],["54","27",{"allocated":0.0,"capacity":1000.0,"flows":[],"id":"100153"}],["27","55",{"allocated":0.0,"capacity":1000.0,"flows":[],"id":"100054"}],["55","27",{"allocated":0.0,"capacity":1000.0,"flows":[],"id":"100154"}],["28","56",{"allocated":0.0,"capacity":1000.0,"flows":[],"id":"100055"}],["56","28",{"allocated":0.0,"capacity":1000.0,"flows":[],"id":"100155"}],["28","57",{"allocated":0.0,"capacity":1000.0,"flows":[],"id":"100056"}],["57","28",{"allocated":0.0,"capacity":1000.0,"flows":[],"id":"100156"}],["29","58",{"allocated":0.0,"capacity":1000.0,"flows":[],"id":"100057"}],["58","29",{"allocated":0.0,"capacity":1000.0,"flows":[],"id":"100157"}],["29","59",{"allocated":0.0,"capacity":1000.0,"flows":[],"id":"100058"}],["59","29",{"allocated":0.0,"capacity":1000.0,"flows":[],"id":"100158"}],["30","60",{"allocated":0.0,"capacity":1000.0,"flows":[],"id":"100059"}],["60","30",{"allocated":0.0,"capacity":1000.0,"flows":[],"id":"100159"}],["30","61",{"allocated":0.0,"capacity":1000.0,"flows":[],"id":"100060"}],["61","30",{"allocated":0.0,"capacity":1000.0,"flows":[],"id":"100160"}],["31","62",{"allocated":0.0,"capacity":1000.0,"flows":[],"id":"100061"}],["62","31",{"allocated":0.0,"capacity":1000.0,"flows":[],"id":"100161"}],["31","63",{"allocated":0.0,"capacity":1000.0,"flows":[],"id":"100062"}],["63","31",{"allocated":0.0,"capacity":1000.0,"flows":[],"id":"100162"}],["32","64",{"allocated":0.0,"capacity":1000.0,"flows":[],"id":"100063"}],["64","32",{"allocated":0.0,"capacity":1000.0,"flows":[],"id":"100163"}],["32","65",{"allocated":0.0,"capacity":1000.0,"flows":[],"id":"100064"}],["65","32",{"allocated":0.0,"capacity":1000.0,"flows":[],"id":"100164"}],["33","66",{"allocated":0.0,"capacity":1000.0,"flows":[],"id":"100065"}],["66","33",{"allocated":0.0,"capacity":1000.0,"flows":[],"id":"100165"}],["33","67",{"allocated":0.0,"capacity":1000.0,"flows":[],"id":"100066"}],["67","33",{"allocated":0.0,"capacity":1000.0,"flows":[],"id":"100166"}],["34","68",{"allocated":0.0,"capacity":1000.0,"flows":[],"id":"100067"}],["68","34",{"allocated":0.0,"capacity":1000.0,"flows":[],"id":"100167"}],["34","69",{"allocated":0.0,"capacity":1000.0,"flows":[],"id":"100068"}],["69","34",{"allocated":0.0,"capacity":1000.0,"flows":[],"id":"100168"}],["35","70",{"allocated":0.0,"capacity":1000.0,"flows":[],"id":"100069"}],["70","35",{"allocated":0.0,"capacity":1000.0,"flows":[],"id":"100169"}],["35","71",{"allocated":0.0,"capacity":1000.0,"flows":[],"id":"100070"}],["71","35",{"allocated":0.0,"capacity":1000.0,"flows":[],"id":"100170"}],["36","72",{"allocated":0.0,"capacity":1000.0,"flows":[],"id":"100071"}],["72","36",{"allocated":0.0,"capacity":1000.0,"flows":[],"id":"100171"}],["36","73",{"allocated":0.0,"capacity":1000.0,"flows":[],"id":"100072"}],["73","36",{"allocated":0.0,"capacity":1000.0,"flows":[],"id":"100172"}],["37","74",{"allocated":0.0,"capacity":1000.0,"flows":[],"id":"100073"}],["74","37",{"allocated":0.0,"capacity":1000.0,"flows":[],"id":"100173"}],["37","75",{"allocated":0.0,"capacity":1000.0,"flows":[],"id":"100074"}],["75","37",{"allocated":0.0,"capacity":1000.0,"flows":[],"id":"100174"}],["38","76",{"allocated":0.0,"capacity":1000.0,"flows":[],"id":"100075"}],["76","38",{"allocated":0.0,"capacity":1000.0,"flows":[],"id":"100175"}],["38","77",{"allocated":0.0,"capacity":1000.0,"flows":[],"id":"100076"}],["77","38",{"allocated":0.0,"capacity":1000.0,"flows":[],"id":"100176"}],["39","78",{"allocated":0.0,"capacity":1000.0,"flows":[],"id":"100077"}],["78","39",{"allocated":0.0,"capacity":1000.0,"flows":[],"id":"100177"}],["39","79",{"allocated":0.0,"capacity":1000.0,"flows":[],"id":"100078"}],["79","39",{"allocated":0.0,"capacity":1000.0,"flows":[],"id":"100178"}],["40","80",{"allocated":0.0,"capacity":1000.0,"flows":[],"id":"100079"}],["80","40",{"allocated":0.0,"capacity":1000.0,"flows":[],"id":"100179"}],["40","81",{"allocated":0.0,"capacity":1000.0,"flows":[],"id":"100080"}],["81","40",{"allocated":0.0,"capacity":1000.0,"flows":[],"id":"100180"}],["41","82",{"allocated":0.0,"capacity":1000.0,"flows":[],"id":"100081"}],["82","41",{"allocated":0.0,"capacity":1000.0,"flows":[],"id":"100181"}],["41","83",{"allocated":0.0,"capacity":1000.0,"flows":[],"id":"100082"}],["83","41",{"allocated":0.0,"capacity":1000.0,"flows":[],"id":"100182"}],["42","84",{"allocated":0.0,"capacity":1000.0,"flows":[],"id":"100083"}],["84","42",{"allocated":0.0,"capacity":1000.0,"flows":[],"id":"100183"}],["42","85",{"allocated":0.0,"capacity":1000.0,"flows":[],"id":"100084"}],["85","42",{"allocated":0.0,"capacity":1000.0,"flows":[],"id":"100184"}],["43","86",{"allocated":0.0,"capacity":1000.0,"flows":[],"id":"100085"}],["86","43",{"allocated":0.0,"capacity":1000.0,"flows":[],"id":"100185"}],["43","87",{"allocated":0.0,"capacity":1000.0,"flows":[],"id":"100086"}],["87","43",{"allocated":0.0,"capacity":1000.0,"flows":[],"id":"100186"}],["44","88",{"allocated":0.0,"capacity":1000.0,"flows":[],"id":"100087"}],["88","44",{"allocated":0.0,"capacity":1000.0,"flows":[],"id":"100187"}],["44","89",{"allocated":0.0,"capacity":1000.0,"flows":[],"id":"100088"}],["89","44",{"allocated":0.0,"capacity":1000.0,"flows":[],"id":"100188"}],["45","90",{"allocated":0.0,"capacity":1000.0,"flows":[],"id":"100089"}],["90","45",{"allocated":0.0,"capacity":1000.0,"flows":[],"id":"100189"}],["45","91",{"allocated":0.0,"capacity":1000.0,"flows":[],"id":"100090"}],["91","45",{"allocated":0.0,"capacity":1000.0,"flows":[],"id":"100190"}],["46","92",{"allocated":0.0,"capacity":1000.0,"flows":[],"id":"100091"}],["92","46",{"allocated":0.0,"capacity":1000.0,"flows":[],"id":"100191"}],["46","93",{"allocated":0.0,"capacity":1000.0,"flows":[],"id":"100092"}],["93","46",{"allocated":0.0,"capacity":1000.0,"flows":[],"id":"100192"}],["47","94",{"allocated":0.0,"capacity":1000.0,"flows":[],"id":"100093"}],["94","47",{"allocated":0.0,"capacity":1000.0,"flows":[],"id":"100193"}],["47","95",{"allocated":0.0,"capacity":1000.0,"flows":[],"id":"100094"}],["95","47",{"allocated":0.0,"capacity":1000.0,"flows":[],"id":"100194"}],["48","96",{"allocated":0.0,"capacity":1000.0,"flows":[],"id":"100095"}],["96","48",{"allocated":0.0,"capacity":1000.0,"flows":[],"id":"100195"}],["48","97",{"allocated":0.0,"capacity":1000.0,"flows":[],"id":"100096"}],["97","48",{"allocated":0.0,"capacity":1000.0,"flows":[],"id":"100196"}],["49","98",{"allocated":0.0,"capacity":1000.0,"flows":[],"id":"100097"}],["98","49",{"allocated":0.0,"capacity":1000.0,"flows":[],"id":"100197"}],["49","99",{"allocated":0.0,"capacity":1000.0,"flows":[],"id":"100098"}],["99","49",{"allocated":0.0,"capacity":1000.0,"flows":[],"id":"100198"}],["50","100",{"allocated":0.0,"capacity":1000.0,"flows":[],"id":"100099"}],["100","50",{"allocated":0.0,"capacity":1000.0,"flows":[],"id":"100199"}],["50","101",{"allocated":0.0,"capacity":1000.0,"flows":[],"id":"1000100"}],["101","50",{"allocated":0.0,"capacity":1000.0,"flows":[],"id":"1001100"}],["51","102",{"allocated":0.0,"capacity":1000.0,"flows":[],"id":"1000101"}],["102","51",{"allocated":0.0,"capacity":1000.0,"flows":[],"id":"1001101"}],["51","103",{"allocated":0.0,"capacity":1000.0,"flows":[],"id":"1000102"}],["103","51",{"allocated":0.0,"capacity":1000.0,"flows":[],"id":"1001102"}],["52","104",{"allocated":0.0,"capacity":1000.0,"flows":[],"id":"1000103"}],["104","52",{"allocated":0.0,"capacity":1000.0,"flows":[],"id":"1001103"}],["52","105",{"allocated":0.0,"capacity":1000.0,"flows":[],"id":"1000104"}],["105","52",{"allocated":0.0,"capacity":1000.0,"flows":[],"id":"1001104"}],["53","106",{"allocated":0.0,"capacity":1000.0,"flows":[],"id":"1000105"}],["106","53",{"allocated":0.0,"capacity":1000.0,"flows":[],"id":"1001105"}],["53","107",{"allocated":0.0,"capacity":1000.0,"flows":[],"id":"1000106"}],["107","53",{"allocated":0.0,"capacity":1000.0,"flows":[],"id":"1001106"}],["54","108",{"allocated":0.0,"capacity":1000.0,"flows":[],"id":"1000107"}],["108","54",{"allocated":0.0,"capacity":1000.0,"flows":[],"id":"1001107"}],["54","109",{"allocated":0.0,"capacity":1000.0,"flows":[],"id":"1000108"}],["109","54",{"allocated":0.0,"capacity":1000.0,"flows":[],"id":"1001108"}],["55","110",{"allocated":0.0,"capacity":1000.0,"flows":[],"id":"1000109"}],["110","55",{"allocated":0.0,"capacity":1000.0,"flows":[],"id":"1001109"}],["55","111",{"allocated":0.0,"capacity":1000.0,"flows":[],"id":"1000110"}],["111","55",{"allocated":0.0,"capacity":1000.0,"flows":[],"id":"1001110"}],["56","112",{"allocated":0.0,"capacity":1000.0,"flows":[],"id":"1000111"}],["112","56",{"allocated":0.0,"capacity":1000.0,"flows":[],"id":"1001111"}],["56","113",{"allocated":0.0,"capacity":1000.0,"flows":[],"id":"1000112"}],["113","56",{"allocated":0.0,"capacity":1000.0,"flows":[],"id":"1001112"}],["57","114",{"allocated":0.0,"capacity":1000.0,"flows":[],"id":"1000113"}],["114","57",{"allocated":0.0,"capacity":1000.0,"flows":[],"id":"1001113"}],["57","115",{"allocated":0.0,"capacity":1000.0,"flows":[],"id":"1000114"}],["115","57",{"allocated":0.0,"capacity":1000.0,"flows":[],"id":"1001114"}],["58","116",{"allocated":0.0,"capacity":1000.0,"flows":[],"id":"1000115"}],["116","58",{"allocated":0.0,"capacity":1000.0,"flows":[],"id":"1001115"}],["58","117",{"allocated":0.0,"capacity":1000.0,"flows":[],"id":"1000116"}],["117","58",{"allocated":0.0,"capacity":1000.0,"flows":[],"id":"1001116"}],["59","118",{"allocated":0.0,"capacity":1000.0,"flows":[],"id":"1000117"}],["118","59",{"allocated":0.0,"capacity":1000.0,"flows":[],"id":"1001117"}],["59","119",{"allocated":0.0,"capacity":1000.0,"flows":[],"id":"1000118"}],["119","59",{"allocated":0.0,"capacity":1000.0,"flows":[],"id":"1001118"}],["60","120",{"allocated":0.0,"capacity":1000.0,"flows":[],"id":"1000119"}],["120","60",{"allocated":0.0,"capacity":1000.0,"flows":[],"id":"1001119"}],["60","121",{"allocated":0.0,"capacity":1000.0,"flows":[],"id":"1000120"}],["121","60",{"allocated":0.0,"capacity":1000.0,"flows":[],"id":"1001120"}],["61","122",{"allocated":0.0,"capacity":1000.0,"flows":[],"id":"1000121"}],["122","61",{"allocated":0.0,"capacity":1000.0,"flows":[],"id":"1001121"}],["61","123",{"allocated":0.0,"capacity":1000.0,"flows":[],"id":"1000122"}],["123","61",{"allocated":0.0,"capacity":1000.0,"flows":[],"id":"1001122"}],["62","124",{"allocated":0.0,"capacity":1000.0,"flows":[],"id":"1000123"}],["124","62",{"allocated":0.0,"capacity":1000.0,"flows":[],"id":"1001123"}],["62","125",{"allocated":0.0,"capacity":1000.0,"flows":[],"id":"1000124"}],["125","62",{"allocated":0.0,"capacity":1000.0,"flows":[],"id":"1001124"}],["63","126",{"allocated":0.0,"capacity":1000.0,"flows":[],"id":"1000125"}],["126","63",{"allocated":0.0,"capacity":1000.0,"flows":[],"id":"1001125"}],["63","127",{"allocated":0.0,"capacity":1000.0,"flows":[],"id":"1000126"}],["127","63",{"allocated":0.0,"capacity":1000.0,"flows":[],"id":"1001126"}]]